{
  "project_info": {
    "project_number": "349160902325",
    "project_id": "coin-vault-85951",
    "storage_bucket": "coin-vault-85951.firebasestorage.app"
  },
  "client": [
    {
      "client_info": {
        "mobilesdk_app_id": "1:349160902325:android:69334a7f5b9f9e55ca78fc",
        "android_client_info": {
          "package_name": "com.navas28.coinvault"
        }
      },
      "oauth_client": [],
      "api_key": [
        {
          "current_key": "AIzaSyDHmDm3UgS1QoHIPs1dOc69ndmy17S0WfQ"
        }
      ],
      "services": {
        "appinvite_service": {
          "other_platform_oauth_client": []
        }
      }
    }
  ],
  "configuration_version": "1"
}